mate/__init__.py
mate/cache.py
mate/keras_trainer.py
mate/lightning_trainer.py
mate/metrics.py
mate/model_checkpoint.py
mate/monitor.py
mate/optimizer.py
mate/trainer.py
mate/__pycache__/__init__.cpython-310.pyc
mate/mate.egg-info/PKG-INFO
mate/mate.egg-info/SOURCES.txt
mate/mate.egg-info/dependency_links.txt
mate/mate.egg-info/requires.txt
mate/mate.egg-info/top_level.txt
mate/migrator/__init__.py
mate/migrator/base_migrator.py
mate/migrator/params_migrator.py
yerbamate/__init__.py
yerbamate/backbone_type.py
yerbamate/constants.py
yerbamate/io.py
yerbamate/logger.py
yerbamate/mate.py
yerbamate/mate_cli.py
yerbamate/mate_config.py
yerbamate/package.py
yerbamate/package_installer.py
yerbamate/__pycache__/__init__.cpython-310.pyc
yerbamate/__pycache__/backbone_type.cpython-310.pyc
yerbamate/__pycache__/io.cpython-310.pyc
yerbamate/__pycache__/mate.cpython-310.pyc
yerbamate/__pycache__/mate_cli.cpython-310.pyc
yerbamate/__pycache__/mate_config.cpython-310.pyc
yerbamate/__pycache__/package.cpython-310.pyc
yerbamate/_legacy/plot.py
yerbamate/_legacy/tune_hyperparameters.py
yerbamate/project_parser/__init__.py
yerbamate/project_parser/_project_parser.py
yerbamate/project_parser/project_parser.py
yerbamate/project_parser/__pycache__/__init__.cpython-310.pyc
yerbamate/project_parser/__pycache__/project_parser.cpython-310.pyc
yerbamate/project_parser/backbone_templates/__init__.py
yerbamate/project_parser/backbone_templates/jax.json
yerbamate/project_parser/backbone_templates/keras.json
yerbamate/project_parser/backbone_templates/lightning.json
yerbamate/trainers/__init__.py
yerbamate/trainers/function_trainer.py
yerbamate/trainers/keras_trainer.py
yerbamate/trainers/lightning_trainer.py
yerbamate/trainers/trainer.py
yerbamate/trainers/__pycache__/__init__.cpython-310.pyc
yerbamate/trainers/__pycache__/keras_trainer.cpython-310.pyc
yerbamate/trainers/__pycache__/lightning_trainer.cpython-310.pyc
yerbamate/trainers/__pycache__/trainer.cpython-310.pyc
yerbamate/utils/__init__.py
yerbamate/utils/bunch.py
yerbamate/utils/git_url_parser.py
yerbamate/utils/migrator.py
yerbamate/utils/utils.py
yerbamate/yerbamate.egg-info/PKG-INFO
yerbamate/yerbamate.egg-info/SOURCES.txt
yerbamate/yerbamate.egg-info/dependency_links.txt
yerbamate/yerbamate.egg-info/top_level.txt
ymdl-0.2.5.dist-info/METADATA
ymdl-0.2.5.dist-info/WHEEL
ymdl-0.2.5.dist-info/top_level.txt
ymdl-0.2.5.dist-info/RECORD
